opendock/core/asl.py
opendock/core/clustering.py
opendock/core/conformation.py
opendock/core/io.py
opendock/core/ligand.py
opendock/core/ligand_origin.py
opendock/core/receptor.py
opendock/core/utils.py
opendock/data/atomtype_mapping.json
opendock/data/bestmodel_cpu.pth
opendock/data/covalent_radii_dict.json
opendock/data/deeprmsd_model_cpu.pth
opendock/data/deeprmsd_train_mean_std.csv
opendock/data/sidechain_topol.json
opendock/data/vdw_radii_dict.json
opendock/sampler/base.py
opendock/sampler/base_origin.py
opendock/sampler/bayesian.py
opendock/sampler/ga.py
opendock/sampler/ga0.py
opendock/sampler/ga_origin.py
opendock/sampler/minimizer.py
opendock/sampler/minimizer1.py
opendock/sampler/monte_carlo.py
opendock/sampler/particle_swarm.py
opendock/sampler/particle_swarm0.py
opendock/sampler/particle_swarm_origin.py
opendock/scorer/bkp.vina.py
opendock/scorer/cmap.py
opendock/scorer/conformer.py
opendock/scorer/constraints.py
opendock/scorer/constraints_origin.py
opendock/scorer/constraints_加角度.py
opendock/scorer/deeprmsd.py
opendock/scorer/general_protocol-elegant-mutlicpu.py
opendock/scorer/hybrid.py
opendock/scorer/onionnet_sfct.py
opendock/scorer/rtmscore.py
opendock/scorer/scoring_function.py
opendock/scorer/vina+C.py
opendock/scorer/vina-origin.py
opendock/scorer/vina-test.py
opendock/scorer/vina.py
opendock/scorer/vina_old.py
opendock/scorer/vina_origin.py
opendock/scorer/xscore.py
opendock/scorer/zPoseRanker.py
opendock/scorer/RTMScore/121.jpg
opendock/scorer/RTMScore/LICENSE
opendock/scorer/RTMScore/README.md
opendock/scorer/RTMScore/requirements_conda.txt
opendock/scorer/RTMScore/requirements_pip.txt
opendock/scorer/RTMScore/utils.py
opendock-0.0.1.dist-info/LICENSE
opendock-0.0.1.dist-info/METADATA
opendock-0.0.1.dist-info/WHEEL
opendock-0.0.1.dist-info/top_level.txt
opendock-0.0.1.dist-info/RECORD
