Metadata-Version: 2.1
Name: opendock
Version: 0.0.1
Summary: Zelixir Open-Docking Framework.
Home-page: 
Author: Qiuyue Hu,Zechen Wang, Liangzhen Zheng
Author-email: qy.hu@siat.ac.cn
License: GPL-3.0
Requires-Python: >=3.6
License-File: LICENSE
Requires-Dist: numpy
Requires-Dist: pandas
